{
  "привет": "Привет! Как дела? Чем могу помочь?",
  "здравствуй": "Здравствуйте! Рад вас видеть. Что вас интересует?",
  "как дела": "У меня всё отлично! А у вас как дела? Могу ли чем-то помочь?",
  "помощь": "Конечно, помогу! Я могу ответить на вопросы о:\n• Регистрации в системе\n• Навигации по сайту\n• Поиске учителей\n• Общих вопросах об образовании",
  "регистрация": "Для регистрации необходимо:\n1. Заполнить email и пароль\n2. Указать настоящие имя и фамилию\n3. Выбрать роль (Ученик/Учитель)\n4. Заполнить дополнительную информацию в зависимости от роли",
  "пароль": "Пароль должен:\n• Содержать минимум 6 символов\n• Включать буквы и цифры\n• Быть достаточно надёжным для защиты аккаунта",
  "учитель": "Если вы учитель, при регистрации укажите:\n• Город, где преподаёте\n• Название школы\n• Предметы, которые ведёте",
  "ученик": "Если вы ученик, при регистрации укажите:\n• Ваш город\n• Название школы\n• Класс, в котором учитесь",
  "найти учителя": "После входа в систему вы сможете посмотреть список всех зарегистрированных учителей с информацией о предметах, которые они преподают.",
  "проблема": "Если у вас возникла проблема, опишите её подробнее, и я постараюсь помочь. Также вы можете обратиться к администратору системы.",
  "спасибо": "Пожалуйста! Всегда рад помочь. Если есть ещё вопросы - спрашивайте!",
  "пока": "До свидания! Удачи в обучении! 👋"
}

